bw_save_game/__init__.py
bw_save_game/container.py
bw_save_game/convert.py
bw_save_game/db_object.py
bw_save_game/db_object_codec.py
bw_save_game/hash.py
bw_save_game/persistence.py
bw_save_game/data/veilguard/archetypes.json
bw_save_game/data/veilguard/collectibles.json
bw_save_game/data/veilguard/currencies.json
bw_save_game/data/veilguard/followers.json
bw_save_game/data/veilguard/items.json
bw_save_game/data/veilguard/maps.json
bw_save_game/data/veilguard/paramdb_keys.json
bw_save_game/data/veilguard/persistence.json
bw_save_game/data/veilguard/quests.json
bw_save_game/data/veilguard/shader_params.json
bw_save_game/data/veilguard/skill_graphs.json
bw_save_game/data/veilguard/textures.json
bw_save_game/data/veilguard/xp_thresholds.json
bw_save_game/ui/__init__.py
bw_save_game/ui/__main__.py
bw_save_game/ui/config.py
bw_save_game/ui/editors.py
bw_save_game/ui/utils.py
bw_save_game/ui/widgets.py
bw_save_game/veilguard/__init__.py
bw_save_game/veilguard/data.py
bw_save_game/veilguard/highlevel.py
bw_save_game/veilguard/paramdb.py
bw_save_game/veilguard/persistence.py
bw_save_game/veilguard/scripts.py
bw_save_game/veilguard/types.py
bw_save_game-1.6.0.dist-info/licenses/LICENSE.txt
bw_save_game-1.6.0.dist-info/METADATA
bw_save_game-1.6.0.dist-info/WHEEL
bw_save_game-1.6.0.dist-info/entry_points.txt
bw_save_game-1.6.0.dist-info/top_level.txt
bw_save_game-1.6.0.dist-info/RECORD
