Metadata-Version: 2.4
Name: bw_save_game
Version: 1.6.0
Summary: Editor for Dragon Age: The Veilguard saves.
Home-page: https://github.com/timniederhausen/bw_save_game
Author: Tim Niederhausen
Author-email: tim@rnc-ag.de
License: GPL-3.0-only
Project-URL: Documentation, https://pyscaffold.org/
Project-URL: Source, https://github.com/timniederhausen/bw_save_game
Platform: any
Classifier: Development Status :: 5 - Production/Stable
Classifier: Programming Language :: Python
Requires-Python: >=3.9
License-File: LICENSE.txt
Requires-Dist: importlib_resources
Provides-Extra: ui
Requires-Dist: imgui_bundle; extra == "ui"
Provides-Extra: testing
Requires-Dist: setuptools; extra == "testing"
Requires-Dist: pytest; extra == "testing"
Requires-Dist: pytest-cov; extra == "testing"
Dynamic: license-file
